gamry_parser/__init__.py
gamry_parser/chronoa.py
gamry_parser/cv.py
gamry_parser/eispot.py
gamry_parser/gamryparser.py
gamry_parser/ocp.py
gamry_parser/squarewave.py
gamry_parser/version.py
gamry_parser/vfp600.py
tests/__init__.py
tests/test_chronoamperometry.py
tests/test_cyclicvoltammetry.py
tests/test_gamryparser.py
tests/test_impedance.py
tests/test_ocp.py
tests/test_squarewave.py
tests/test_vfp600.py
gamry_parser-0.4.6.dist-info/LICENSE
gamry_parser-0.4.6.dist-info/METADATA
gamry_parser-0.4.6.dist-info/WHEEL
gamry_parser-0.4.6.dist-info/top_level.txt
gamry_parser-0.4.6.dist-info/RECORD
