Metadata-Version: 2.1
Name: gamry-parser
Version: 0.4.6
Summary: Package for parsing the contents of Gamry EXPLAIN data (DTA) files.
Home-page: https://github.com/bcliang/gamry-parser
Author: Brad Liang
Author-email: brad.liang@percusense.com
License: MIT
Keywords: gamry electrochemistry EXPLAIN DTA parser
Platform: UNKNOWN
Classifier: License :: OSI Approved :: MIT License
Classifier: Programming Language :: Python
Classifier: Programming Language :: Python :: 3
License-File: LICENSE
Requires-Dist: pandas
